
<week>
    <day which="mon">
        <weekslot time="1030" class="ACIT4650">
            <instructor>Medhat Elmasry</instructor>
            <room>SE12-306</room>
        </weekslot>
        <weekslot time="1130" class="ACIT4650">
            <instructor>Medhat Elmasry</instructor>
            <room>SE12-306</room>
        </weekslot>
        <weekslot time="1530" class="ACIT4650">
            <instructor>Richard Chau</instructor>
            <room>SW9-206</room>
        </weekslot>
        <weekslot time="1630" class="ACIT4650">
            <instructor>Medhat Elmasry</instructor>
            <room>SE6-205</room>
        </weekslot>
    </day>
    <day which="tue">
        <weekslot time="0830" class="ACIT4620">
            <instructor>Bethany Edmonds</instructor>
            <room>SE12-306</room>
        </weekslot>
        <weekslot time="0930" class="ACIT4620">
            <instructor>Bethany Edmonds</instructor>
            <room>SE12-306</room>
        </weekslot>
        <weekslot time="1230" class="ACIT4650">
            <instructor>Medhat Elmasry</instructor>
            <room>SW9-206</room>
        </weekslot>
        <weekslot time="1430" class="ACIT4620">
            <instructor>Bethany Edmonds</instructor>
            <room>SW9-206</room>
        </weekslot>
        <weekslot time="1530" class="ACIT4620">
            <instructor>Bethany Edmonds</instructor>
            <room>SW9-206</room>
        </weekslot>
    </day>
     <day which="thu">
        <weekslot time="0930" class="ACIT4910">
            <instructor>Richard Chau</instructor>
            <room>SW5-1840</room>
        </weekslot>
        <weekslot time="1030" class="ACIT4910">
            <instructor>Richard Chau</instructor>
            <room>SE12-306</room>
        </weekslot>
        <weekslot time="1330" class="ACIT4850">
            <instructor>James Parry</instructor>
            <room>SE12-308</room>
        </weekslot>
       
    </day>
</week>
